tamu_csce_636_project1/__init__.py
tamu_csce_636_project1/main.py
tamu_csce_636_project1/settings.json
tamu_csce_636_project1/__dependencies__/__init__.py
tamu_csce_636_project1/__dependencies__/__sources__/.keep
tamu_csce_636_project1/__pycache__/__init__.cpython-38.pyc
tamu_csce_636_project1/__pycache__/main.cpython-38.pyc
tamu_csce_636_project1-0.0.7.dist-info/METADATA
tamu_csce_636_project1-0.0.7.dist-info/WHEEL
tamu_csce_636_project1-0.0.7.dist-info/top_level.txt
tamu_csce_636_project1-0.0.7.dist-info/RECORD
