Metadata-Version: 2.1
Name: tamu-csce-636-project1
Version: 0.0.7
Summary: Just a tool for tamu_csce_636
Home-page: https://github.com/jeff-hykin/tamu_csce_636_project1
Author: Jeff hykin
Author-email: jeff.hykin+pypi@gmail.com
License: MIT
Platform: UNKNOWN
Requires-Python: >=3.6
